{"cameraMode":{"drawMode":0,"name":"Shaded","section":"Shading Mode"},"sceneLighting":true,"audioPlay":false,"sceneViewState":{"showFog":true,"showMaterialUpdate":false,"showSkybox":true,"showFlares":true,"showImageEffects":true,"showParticleSystems":true},"in2DMode":false,"pivot":{"x":-276.9466857910156,"y":91.63554382324219,"z":2.4128952026367189},"rotation":{"x":-0.01012107077986002,"y":0.9665236473083496,"z":-0.2538173496723175,"w":-0.03872404620051384},"size":4.1263108253479,"orthographic":false}